encrypted_mysqldb/__init__.py
encrypted_mysqldb/connection_pool.py
encrypted_mysqldb/crypt.py
encrypted_mysqldb/database.py
encrypted_mysqldb/errors.py
encrypted_mysqldb/table.py
encrypted_mysqldb/fields/__init__.py
encrypted_mysqldb/fields/base_field.py
encrypted_mysqldb/fields/bool_field.py
encrypted_mysqldb/fields/datetime_field.py
encrypted_mysqldb/fields/hash_field.py
encrypted_mysqldb/fields/id_field.py
encrypted_mysqldb/fields/int_field.py
encrypted_mysqldb/fields/list_field.py
encrypted_mysqldb/fields/set_field.py
encrypted_mysqldb/fields/str_field.py
encrypted_mysqldb-1.0.0.dist-info/LICENSE
encrypted_mysqldb-1.0.0.dist-info/METADATA
encrypted_mysqldb-1.0.0.dist-info/WHEEL
encrypted_mysqldb-1.0.0.dist-info/top_level.txt
encrypted_mysqldb-1.0.0.dist-info/RECORD
