Metadata-Version: 2.1
Name: encrypted-mysqldb
Version: 1.0.0
Summary: A basic interface to Mysqldb library with integrated encryption
Home-page: https://github.com/SpartanPlume/encrypted-mysqldb
Author: Spartan Plume
Author-email: spartan.plume@gmail.com
License: MIT
Keywords: mysqldb mysql encrypted-mysqldb encrypted_mysqldb encryption hash db database mariadb
License-File: LICENSE
Requires-Dist: mysql-connector-python
Requires-Dist: inflection
